[
  {
    "t": "mouse_move",
    "dt": 0.0397442999528721,
    "data": {
      "x": 1535,
      "y": 837
    }
  },
  {
    "t": "mouse_move",
    "dt": 0.05581389996223152,
    "data": {
      "x": 1536,
      "y": 837
    }
  },
  {
    "t": "mouse_move",
    "dt": 0.07980019995011389,
    "data": {
      "x": 1536,
      "y": 836
    }
  },
  {
    "t": "mouse_move",
    "dt": 0.09572670003399253,
    "data": {
      "x": 1536,
      "y": 835
    }
  },
  {
    "t": "mouse_move",
    "dt": 0.1042128000408411,
    "data": {
      "x": 1536,
      "y": 833
    }
  },
  {
    "t": "mouse_move",
    "dt": 0.11170989996753633,
    "data": {
      "x": 1536,
      "y": 831
    }
  },
  {
    "t": "mouse_move",
    "dt": 0.11968979996163398,
    "data": {
      "x": 1536,
      "y": 830
    }
  },
  {
    "t": "mouse_move",
    "dt": 0.1277970999944955,
    "data": {
      "x": 1536,
      "y": 828
    }
  },
  {
    "t": "mouse_move",
    "dt": 0.13576520001515746,
    "data": {
      "x": 1536,
      "y": 824
    }
  },
  {
    "t": "mouse_move",
    "dt": 0.14379689993802458,
    "data": {
      "x": 1536,
      "y": 821
    }
  },
  {
    "t": "mouse_move",
    "dt": 0.15182749996893108,
    "data": {
      "x": 1536,
      "y": 817
    }
  },
  {
    "t": "mouse_move",
    "dt": 0.15978949994314462,
    "data": {
      "x": 1536,
      "y": 812
    }
  },
  {
    "t": "mouse_move",
    "dt": 0.167811100021936,
    "data": {
      "x": 1535,
      "y": 806
    }
  },
  {
    "t": "mouse_move",
    "dt": 0.17577979993075132,
    "data": {
      "x": 1532,
      "y": 799
    }
  },
  {
    "t": "mouse_move",
    "dt": 0.18380350002553314,
    "data": {
      "x": 1529,
      "y": 790
    }
  },
  {
    "t": "mouse_move",
    "dt": 0.19173249998129904,
    "data": {
      "x": 1526,
      "y": 783
    }
  },
  {
    "t": "mouse_move",
    "dt": 0.19973859994206578,
    "data": {
      "x": 1522,
      "y": 775
    }
  },
  {
    "t": "mouse_move",
    "dt": 0.20775389997288585,
    "data": {
      "x": 1516,
      "y": 766
    }
  },
  {
    "t": "mouse_move",
    "dt": 0.2158699999563396,
    "data": {
      "x": 1508,
      "y": 756
    }
  },
  {
    "t": "mouse_move",
    "dt": 0.2237697000382468,
    "data": {
      "x": 1499,
      "y": 745
    }
  },
  {
    "t": "mouse_move",
    "dt": 0.23178679996635765,
    "data": {
      "x": 1487,
      "y": 734
    }
  },
  {
    "t": "mouse_move",
    "dt": 0.23983059998136014,
    "data": {
      "x": 1474,
      "y": 722
    }
  },
  {
    "t": "mouse_move",
    "dt": 0.2478265999816358,
    "data": {
      "x": 1459,
      "y": 711
    }
  },
  {
    "t": "mouse_move",
    "dt": 0.2557699999306351,
    "data": {
      "x": 1442,
      "y": 701
    }
  },
  {
    "t": "mouse_move",
    "dt": 0.2637253999710083,
    "data": {
      "x": 1423,
      "y": 690
    }
  },
  {
    "t": "mouse_move",
    "dt": 0.271827399963513,
    "data": {
      "x": 1401,
      "y": 681
    }
  },
  {
    "t": "mouse_move",
    "dt": 0.2797978000016883,
    "data": {
      "x": 1376,
      "y": 673
    }
  },
  {
    "t": "mouse_move",
    "dt": 0.2877747999737039,
    "data": {
      "x": 1348,
      "y": 665
    }
  },
  {
    "t": "mouse_move",
    "dt": 0.29569830000400543,
    "data": {
      "x": 1307,
      "y": 656
    }
  },
  {
    "t": "mouse_move",
    "dt": 0.30371130001731217,
    "data": {
      "x": 1263,
      "y": 646
    }
  },
  {
    "t": "mouse_move",
    "dt": 0.311786700040102,
    "data": {
      "x": 1215,
      "y": 636
    }
  },
  {
    "t": "mouse_move",
    "dt": 0.3197073999326676,
    "data": {
      "x": 1172,
      "y": 629
    }
  },
  {
    "t": "mouse_move",
    "dt": 0.3277051999466494,
    "data": {
      "x": 1125,
      "y": 621
    }
  },
  {
    "t": "mouse_move",
    "dt": 0.3374327999772504,
    "data": {
      "x": 1082,
      "y": 614
    }
  },
  {
    "t": "mouse_move",
    "dt": 0.3437627999810502,
    "data": {
      "x": 1039,
      "y": 609
    }
  },
  {
    "t": "mouse_move",
    "dt": 0.3517353000352159,
    "data": {
      "x": 997,
      "y": 605
    }
  },
  {
    "t": "mouse_move",
    "dt": 0.3596844000276178,
    "data": {
      "x": 958,
      "y": 600
    }
  },
  {
    "t": "mouse_move",
    "dt": 0.36768240004312247,
    "data": {
      "x": 924,
      "y": 598
    }
  },
  {
    "t": "mouse_move",
    "dt": 0.3757455999730155,
    "data": {
      "x": 894,
      "y": 596
    }
  },
  {
    "t": "mouse_move",
    "dt": 0.3839185000397265,
    "data": {
      "x": 867,
      "y": 592
    }
  },
  {
    "t": "mouse_move",
    "dt": 0.391714800032787,
    "data": {
      "x": 842,
      "y": 590
    }
  },
  {
    "t": "mouse_move",
    "dt": 0.3996977999340743,
    "data": {
      "x": 820,
      "y": 590
    }
  },
  {
    "t": "mouse_move",
    "dt": 0.40770109998993576,
    "data": {
      "x": 800,
      "y": 590
    }
  },
  {
    "t": "mouse_move",
    "dt": 0.4158688000170514,
    "data": {
      "x": 780,
      "y": 590
    }
  },
  {
    "t": "mouse_move",
    "dt": 0.423685000045225,
    "data": {
      "x": 762,
      "y": 590
    }
  },
  {
    "t": "mouse_move",
    "dt": 0.4316230999538675,
    "data": {
      "x": 746,
      "y": 591
    }
  },
  {
    "t": "mouse_move",
    "dt": 0.4397808000212535,
    "data": {
      "x": 734,
      "y": 591
    }
  },
  {
    "t": "mouse_move",
    "dt": 0.44766980002168566,
    "data": {
      "x": 724,
      "y": 591
    }
  },
  {
    "t": "mouse_move",
    "dt": 0.4557203999720514,
    "data": {
      "x": 718,
      "y": 592
    }
  },
  {
    "t": "mouse_move",
    "dt": 0.4637950999895111,
    "data": {
      "x": 714,
      "y": 592
    }
  },
  {
    "t": "mouse_move",
    "dt": 0.47177139995619655,
    "data": {
      "x": 713,
      "y": 592
    }
  },
  {
    "t": "mouse_move",
    "dt": 0.47977249999530613,
    "data": {
      "x": 713,
      "y": 592
    }
  },
  {
    "t": "mouse_move",
    "dt": 0.48775329999625683,
    "data": {
      "x": 714,
      "y": 590
    }
  },
  {
    "t": "mouse_move",
    "dt": 0.4957204000093043,
    "data": {
      "x": 718,
      "y": 585
    }
  },
  {
    "t": "mouse_move",
    "dt": 0.5036680999910459,
    "data": {
      "x": 723,
      "y": 582
    }
  },
  {
    "t": "mouse_move",
    "dt": 0.5117528999689966,
    "data": {
      "x": 727,
      "y": 580
    }
  },
  {
    "t": "mouse_move",
    "dt": 0.5197738000424579,
    "data": {
      "x": 727,
      "y": 580
    }
  },
  {
    "t": "mouse_move",
    "dt": 0.5278007000451908,
    "data": {
      "x": 728,
      "y": 580
    }
  },
  {
    "t": "mouse_move",
    "dt": 0.6397418000269681,
    "data": {
      "x": 728,
      "y": 580
    }
  },
  {
    "t": "mouse_move",
    "dt": 0.6482327999547124,
    "data": {
      "x": 728,
      "y": 585
    }
  },
  {
    "t": "mouse_move",
    "dt": 0.6557263999711722,
    "data": {
      "x": 728,
      "y": 589
    }
  },
  {
    "t": "mouse_move",
    "dt": 0.6637405999936163,
    "data": {
      "x": 728,
      "y": 594
    }
  },
  {
    "t": "mouse_move",
    "dt": 0.6716633000178263,
    "data": {
      "x": 728,
      "y": 598
    }
  },
  {
    "t": "mouse_move",
    "dt": 0.6799417999573052,
    "data": {
      "x": 728,
      "y": 602
    }
  },
  {
    "t": "mouse_move",
    "dt": 0.6877338000340387,
    "data": {
      "x": 728,
      "y": 603
    }
  },
  {
    "t": "mouse_move",
    "dt": 0.6956800000043586,
    "data": {
      "x": 728,
      "y": 604
    }
  },
  {
    "t": "mouse_move",
    "dt": 0.703732099966146,
    "data": {
      "x": 728,
      "y": 605
    }
  },
  {
    "t": "mouse_move",
    "dt": 0.7358334000455216,
    "data": {
      "x": 728,
      "y": 604
    }
  },
  {
    "t": "mouse_move",
    "dt": 0.7441074999514967,
    "data": {
      "x": 726,
      "y": 601
    }
  },
  {
    "t": "mouse_move",
    "dt": 0.7517577999969944,
    "data": {
      "x": 722,
      "y": 596
    }
  },
  {
    "t": "mouse_move",
    "dt": 0.7600547999609262,
    "data": {
      "x": 718,
      "y": 589
    }
  },
  {
    "t": "mouse_move",
    "dt": 0.7677588999504223,
    "data": {
      "x": 715,
      "y": 580
    }
  },
  {
    "t": "mouse_move",
    "dt": 0.7757359000388533,
    "data": {
      "x": 712,
      "y": 572
    }
  },
  {
    "t": "mouse_move",
    "dt": 0.7837991999695078,
    "data": {
      "x": 710,
      "y": 563
    }
  },
  {
    "t": "mouse_move",
    "dt": 0.7918111999752,
    "data": {
      "x": 708,
      "y": 557
    }
  },
  {
    "t": "mouse_move",
    "dt": 0.7998566000023857,
    "data": {
      "x": 708,
      "y": 552
    }
  },
  {
    "t": "mouse_move",
    "dt": 0.8078546000178903,
    "data": {
      "x": 708,
      "y": 548
    }
  },
  {
    "t": "mouse_move",
    "dt": 0.8158662000205368,
    "data": {
      "x": 708,
      "y": 544
    }
  },
  {
    "t": "mouse_move",
    "dt": 0.8237757999449968,
    "data": {
      "x": 708,
      "y": 542
    }
  },
  {
    "t": "mouse_move",
    "dt": 0.8317761999787763,
    "data": {
      "x": 708,
      "y": 540
    }
  },
  {
    "t": "mouse_move",
    "dt": 0.8397010000189766,
    "data": {
      "x": 708,
      "y": 537
    }
  },
  {
    "t": "mouse_move",
    "dt": 0.8477318999357522,
    "data": {
      "x": 709,
      "y": 535
    }
  },
  {
    "t": "mouse_move",
    "dt": 0.8557687000138685,
    "data": {
      "x": 709,
      "y": 532
    }
  },
  {
    "t": "mouse_move",
    "dt": 0.8637727999594063,
    "data": {
      "x": 709,
      "y": 529
    }
  },
  {
    "t": "mouse_move",
    "dt": 0.8717905000085011,
    "data": {
      "x": 709,
      "y": 526
    }
  },
  {
    "t": "mouse_move",
    "dt": 0.8798249999526888,
    "data": {
      "x": 709,
      "y": 522
    }
  },
  {
    "t": "mouse_move",
    "dt": 0.8877594999503344,
    "data": {
      "x": 709,
      "y": 518
    }
  },
  {
    "t": "mouse_move",
    "dt": 0.89574339997489,
    "data": {
      "x": 709,
      "y": 513
    }
  },
  {
    "t": "mouse_move",
    "dt": 0.9036959999939427,
    "data": {
      "x": 709,
      "y": 510
    }
  },
  {
    "t": "mouse_move",
    "dt": 0.9116855999454856,
    "data": {
      "x": 709,
      "y": 507
    }
  },
  {
    "t": "mouse_move",
    "dt": 0.9197250000433996,
    "data": {
      "x": 709,
      "y": 504
    }
  },
  {
    "t": "mouse_move",
    "dt": 0.9277274999767542,
    "data": {
      "x": 708,
      "y": 500
    }
  },
  {
    "t": "mouse_move",
    "dt": 0.9357134000165388,
    "data": {
      "x": 708,
      "y": 497
    }
  },
  {
    "t": "mouse_move",
    "dt": 0.9436993999406695,
    "data": {
      "x": 708,
      "y": 494
    }
  },
  {
    "t": "mouse_move",
    "dt": 0.9516857999842614,
    "data": {
      "x": 707,
      "y": 492
    }
  },
  {
    "t": "mouse_move",
    "dt": 0.9596846000058576,
    "data": {
      "x": 707,
      "y": 491
    }
  },
  {
    "t": "mouse_move",
    "dt": 0.9677536999806762,
    "data": {
      "x": 707,
      "y": 490
    }
  },
  {
    "t": "mouse_move",
    "dt": 0.9756917000049725,
    "data": {
      "x": 707,
      "y": 489
    }
  },
  {
    "t": "mouse_move",
    "dt": 0.9917434999952093,
    "data": {
      "x": 707,
      "y": 488
    }
  },
  {
    "t": "mouse_move",
    "dt": 0.9997102000052109,
    "data": {
      "x": 707,
      "y": 488
    }
  },
  {
    "t": "mouse_move",
    "dt": 1.2639009000267833,
    "data": {
      "x": 707,
      "y": 486
    }
  },
  {
    "t": "mouse_move",
    "dt": 1.272198099992238,
    "data": {
      "x": 707,
      "y": 483
    }
  },
  {
    "t": "mouse_move",
    "dt": 1.2797164999647066,
    "data": {
      "x": 707,
      "y": 478
    }
  },
  {
    "t": "mouse_move",
    "dt": 1.2879558999557048,
    "data": {
      "x": 707,
      "y": 472
    }
  },
  {
    "t": "mouse_move",
    "dt": 1.295679899980314,
    "data": {
      "x": 707,
      "y": 466
    }
  },
  {
    "t": "mouse_move",
    "dt": 1.303816600004211,
    "data": {
      "x": 707,
      "y": 460
    }
  },
  {
    "t": "mouse_move",
    "dt": 1.3116953000426292,
    "data": {
      "x": 707,
      "y": 455
    }
  },
  {
    "t": "mouse_move",
    "dt": 1.319952299934812,
    "data": {
      "x": 707,
      "y": 452
    }
  },
  {
    "t": "mouse_move",
    "dt": 1.3277080999687314,
    "data": {
      "x": 707,
      "y": 449
    }
  },
  {
    "t": "mouse_move",
    "dt": 1.335836400045082,
    "data": {
      "x": 707,
      "y": 446
    }
  },
  {
    "t": "mouse_move",
    "dt": 1.3437894999515265,
    "data": {
      "x": 707,
      "y": 442
    }
  },
  {
    "t": "mouse_move",
    "dt": 1.351808900013566,
    "data": {
      "x": 708,
      "y": 439
    }
  },
  {
    "t": "mouse_move",
    "dt": 1.35975469998084,
    "data": {
      "x": 709,
      "y": 434
    }
  },
  {
    "t": "mouse_move",
    "dt": 1.3677417000290006,
    "data": {
      "x": 709,
      "y": 431
    }
  },
  {
    "t": "mouse_move",
    "dt": 1.3758021999383345,
    "data": {
      "x": 711,
      "y": 427
    }
  },
  {
    "t": "mouse_move",
    "dt": 1.383774199988693,
    "data": {
      "x": 711,
      "y": 423
    }
  },
  {
    "t": "mouse_move",
    "dt": 1.3917608000338078,
    "data": {
      "x": 711,
      "y": 420
    }
  },
  {
    "t": "mouse_move",
    "dt": 1.399771900032647,
    "data": {
      "x": 712,
      "y": 417
    }
  },
  {
    "t": "mouse_move",
    "dt": 1.4076819999609143,
    "data": {
      "x": 713,
      "y": 415
    }
  },
  {
    "t": "mouse_move",
    "dt": 1.415733400033787,
    "data": {
      "x": 713,
      "y": 413
    }
  },
  {
    "t": "mouse_move",
    "dt": 1.4237818999681622,
    "data": {
      "x": 714,
      "y": 411
    }
  },
  {
    "t": "mouse_move",
    "dt": 1.4317877000430599,
    "data": {
      "x": 714,
      "y": 409
    }
  },
  {
    "t": "mouse_move",
    "dt": 1.4398040999658406,
    "data": {
      "x": 714,
      "y": 408
    }
  },
  {
    "t": "mouse_move",
    "dt": 1.4476968999952078,
    "data": {
      "x": 715,
      "y": 407
    }
  },
  {
    "t": "mouse_move",
    "dt": 1.4557821999769658,
    "data": {
      "x": 715,
      "y": 406
    }
  },
  {
    "t": "mouse_move",
    "dt": 1.4637927999719977,
    "data": {
      "x": 715,
      "y": 406
    }
  },
  {
    "t": "mouse_move",
    "dt": 1.536001699976623,
    "data": {
      "x": 715,
      "y": 405
    }
  },
  {
    "t": "mouse_move",
    "dt": 1.5438136999728158,
    "data": {
      "x": 715,
      "y": 405
    }
  },
  {
    "t": "mouse_click",
    "dt": 1.6483786000171676,
    "data": {
      "x": 715,
      "y": 405,
      "button": "left",
      "pressed": true
    }
  },
  {
    "t": "mouse_click",
    "dt": 1.6961739000398666,
    "data": {
      "x": 715,
      "y": 405,
      "button": "left",
      "pressed": false
    }
  },
  {
    "t": "mouse_move",
    "dt": 1.8078593999380246,
    "data": {
      "x": 716,
      "y": 405
    }
  },
  {
    "t": "mouse_move",
    "dt": 1.8159213999751955,
    "data": {
      "x": 718,
      "y": 405
    }
  },
  {
    "t": "mouse_move",
    "dt": 1.8239041999913752,
    "data": {
      "x": 723,
      "y": 406
    }
  },
  {
    "t": "mouse_move",
    "dt": 1.8318444000324234,
    "data": {
      "x": 730,
      "y": 409
    }
  },
  {
    "t": "mouse_move",
    "dt": 1.8397714999737218,
    "data": {
      "x": 740,
      "y": 413
    }
  },
  {
    "t": "mouse_move",
    "dt": 1.847797799971886,
    "data": {
      "x": 753,
      "y": 421
    }
  },
  {
    "t": "mouse_move",
    "dt": 1.85579299996607,
    "data": {
      "x": 768,
      "y": 429
    }
  },
  {
    "t": "mouse_move",
    "dt": 1.8638634999515489,
    "data": {
      "x": 787,
      "y": 440
    }
  },
  {
    "t": "mouse_move",
    "dt": 1.8718092000344768,
    "data": {
      "x": 814,
      "y": 452
    }
  },
  {
    "t": "mouse_move",
    "dt": 1.8798157999990508,
    "data": {
      "x": 845,
      "y": 470
    }
  },
  {
    "t": "mouse_move",
    "dt": 1.8878218999598175,
    "data": {
      "x": 888,
      "y": 490
    }
  },
  {
    "t": "mouse_move",
    "dt": 1.8959589999867603,
    "data": {
      "x": 936,
      "y": 517
    }
  },
  {
    "t": "mouse_move",
    "dt": 1.9037571999942884,
    "data": {
      "x": 996,
      "y": 548
    }
  },
  {
    "t": "mouse_move",
    "dt": 1.9116778000025079,
    "data": {
      "x": 1052,
      "y": 582
    }
  },
  {
    "t": "mouse_move",
    "dt": 1.9196668999502435,
    "data": {
      "x": 1108,
      "y": 616
    }
  },
  {
    "t": "mouse_move",
    "dt": 1.9276931999484077,
    "data": {
      "x": 1161,
      "y": 652
    }
  },
  {
    "t": "mouse_move",
    "dt": 1.9357154000317678,
    "data": {
      "x": 1210,
      "y": 687
    }
  },
  {
    "t": "mouse_move",
    "dt": 1.9437505999812856,
    "data": {
      "x": 1248,
      "y": 718
    }
  },
  {
    "t": "mouse_move",
    "dt": 1.951780500006862,
    "data": {
      "x": 1279,
      "y": 749
    }
  },
  {
    "t": "mouse_move",
    "dt": 1.9601156000280753,
    "data": {
      "x": 1301,
      "y": 775
    }
  },
  {
    "t": "mouse_move",
    "dt": 1.9677869000006467,
    "data": {
      "x": 1318,
      "y": 803
    }
  },
  {
    "t": "mouse_move",
    "dt": 1.9757428000448272,
    "data": {
      "x": 1328,
      "y": 825
    }
  },
  {
    "t": "mouse_move",
    "dt": 1.9837379000382498,
    "data": {
      "x": 1331,
      "y": 844
    }
  },
  {
    "t": "mouse_move",
    "dt": 1.9918549000285566,
    "data": {
      "x": 1333,
      "y": 860
    }
  },
  {
    "t": "mouse_move",
    "dt": 1.999740200000815,
    "data": {
      "x": 1333,
      "y": 876
    }
  },
  {
    "t": "mouse_move",
    "dt": 2.008024699985981,
    "data": {
      "x": 1330,
      "y": 890
    }
  },
  {
    "t": "mouse_move",
    "dt": 2.0158507999731228,
    "data": {
      "x": 1326,
      "y": 903
    }
  },
  {
    "t": "mouse_move",
    "dt": 2.0238421999383718,
    "data": {
      "x": 1321,
      "y": 915
    }
  },
  {
    "t": "mouse_move",
    "dt": 2.0317813999718055,
    "data": {
      "x": 1316,
      "y": 926
    }
  },
  {
    "t": "mouse_move",
    "dt": 2.039792999974452,
    "data": {
      "x": 1312,
      "y": 937
    }
  },
  {
    "t": "mouse_move",
    "dt": 2.047834899974987,
    "data": {
      "x": 1306,
      "y": 946
    }
  },
  {
    "t": "mouse_move",
    "dt": 2.0557759000221267,
    "data": {
      "x": 1300,
      "y": 955
    }
  },
  {
    "t": "mouse_move",
    "dt": 2.0637540000025183,
    "data": {
      "x": 1294,
      "y": 962
    }
  },
  {
    "t": "mouse_move",
    "dt": 2.0719099999405444,
    "data": {
      "x": 1287,
      "y": 968
    }
  },
  {
    "t": "mouse_move",
    "dt": 2.0797551999567077,
    "data": {
      "x": 1279,
      "y": 975
    }
  },
  {
    "t": "mouse_move",
    "dt": 2.087768299970776,
    "data": {
      "x": 1272,
      "y": 981
    }
  },
  {
    "t": "mouse_move",
    "dt": 2.0957086000125855,
    "data": {
      "x": 1265,
      "y": 987
    }
  },
  {
    "t": "mouse_move",
    "dt": 2.103721100022085,
    "data": {
      "x": 1260,
      "y": 990
    }
  },
  {
    "t": "mouse_move",
    "dt": 2.111681399983354,
    "data": {
      "x": 1255,
      "y": 994
    }
  },
  {
    "t": "mouse_move",
    "dt": 2.119750199955888,
    "data": {
      "x": 1250,
      "y": 997
    }
  },
  {
    "t": "mouse_move",
    "dt": 2.1277486999752,
    "data": {
      "x": 1246,
      "y": 999
    }
  },
  {
    "t": "mouse_move",
    "dt": 2.135803799959831,
    "data": {
      "x": 1243,
      "y": 1001
    }
  },
  {
    "t": "mouse_move",
    "dt": 2.1437550999689847,
    "data": {
      "x": 1241,
      "y": 1002
    }
  },
  {
    "t": "mouse_move",
    "dt": 2.1517548999981955,
    "data": {
      "x": 1239,
      "y": 1003
    }
  },
  {
    "t": "mouse_move",
    "dt": 2.159751099999994,
    "data": {
      "x": 1237,
      "y": 1004
    }
  },
  {
    "t": "mouse_move",
    "dt": 2.1677640000125393,
    "data": {
      "x": 1233,
      "y": 1007
    }
  },
  {
    "t": "mouse_move",
    "dt": 2.175810999935493,
    "data": {
      "x": 1231,
      "y": 1008
    }
  },
  {
    "t": "mouse_move",
    "dt": 2.1837578000267968,
    "data": {
      "x": 1229,
      "y": 1009
    }
  },
  {
    "t": "mouse_move",
    "dt": 2.191835799952969,
    "data": {
      "x": 1227,
      "y": 1010
    }
  },
  {
    "t": "mouse_move",
    "dt": 2.1997536999406293,
    "data": {
      "x": 1225,
      "y": 1011
    }
  },
  {
    "t": "mouse_move",
    "dt": 2.2077133000129834,
    "data": {
      "x": 1223,
      "y": 1012
    }
  },
  {
    "t": "mouse_move",
    "dt": 2.215713799931109,
    "data": {
      "x": 1221,
      "y": 1013
    }
  },
  {
    "t": "mouse_move",
    "dt": 2.2242519999854267,
    "data": {
      "x": 1219,
      "y": 1015
    }
  },
  {
    "t": "mouse_move",
    "dt": 2.2317507000407204,
    "data": {
      "x": 1217,
      "y": 1017
    }
  },
  {
    "t": "mouse_move",
    "dt": 2.239776400034316,
    "data": {
      "x": 1215,
      "y": 1019
    }
  },
  {
    "t": "mouse_move",
    "dt": 2.247778999968432,
    "data": {
      "x": 1211,
      "y": 1021
    }
  },
  {
    "t": "mouse_move",
    "dt": 2.2558013999368995,
    "data": {
      "x": 1209,
      "y": 1022
    }
  },
  {
    "t": "mouse_move",
    "dt": 2.2637128999922425,
    "data": {
      "x": 1207,
      "y": 1023
    }
  },
  {
    "t": "mouse_move",
    "dt": 2.2717568000080064,
    "data": {
      "x": 1206,
      "y": 1024
    }
  },
  {
    "t": "mouse_move",
    "dt": 2.279812699998729,
    "data": {
      "x": 1205,
      "y": 1024
    }
  },
  {
    "t": "mouse_click",
    "dt": 2.3763956000329927,
    "data": {
      "x": 1205,
      "y": 1024,
      "button": "left",
      "pressed": true
    }
  },
  {
    "t": "mouse_click",
    "dt": 2.4163510999642313,
    "data": {
      "x": 1205,
      "y": 1024,
      "button": "left",
      "pressed": false
    }
  },
  {
    "t": "key_press",
    "dt": 3.0648903000401333,
    "data": {
      "key": "1"
    }
  },
  {
    "t": "key_press",
    "dt": 3.1931671999627724,
    "data": {
      "key": "2"
    }
  },
  {
    "t": "key_release",
    "dt": 3.2576291000004858,
    "data": {
      "key": "1"
    }
  },
  {
    "t": "key_press",
    "dt": 3.2972518999595195,
    "data": {
      "key": "3"
    }
  },
  {
    "t": "key_release",
    "dt": 3.34613179997541,
    "data": {
      "key": "2"
    }
  },
  {
    "t": "key_release",
    "dt": 3.385933200013824,
    "data": {
      "key": "3"
    }
  },
  {
    "t": "key_press",
    "dt": 3.489515300025232,
    "data": {
      "key": "4"
    }
  },
  {
    "t": "key_release",
    "dt": 3.577068999991752,
    "data": {
      "key": "4"
    }
  },
  {
    "t": "key_press",
    "dt": 3.6253230000147596,
    "data": {
      "key": "5"
    }
  },
  {
    "t": "key_release",
    "dt": 3.6890005000168458,
    "data": {
      "key": "5"
    }
  },
  {
    "t": "key_press",
    "dt": 3.8181544999824837,
    "data": {
      "key": "6"
    }
  },
  {
    "t": "key_release",
    "dt": 3.8651810999726877,
    "data": {
      "key": "6"
    }
  },
  {
    "t": "key_press",
    "dt": 4.601405399967916,
    "data": {
      "key": "Key.enter"
    }
  },
  {
    "t": "key_release",
    "dt": 4.672381400014274,
    "data": {
      "key": "Key.enter"
    }
  },
  {
    "t": "mouse_move",
    "dt": 5.735807799967006,
    "data": {
      "x": 1205,
      "y": 1024
    }
  },
  {
    "t": "mouse_move",
    "dt": 5.743763500009663,
    "data": {
      "x": 1207,
      "y": 1021
    }
  },
  {
    "t": "mouse_move",
    "dt": 5.751734199933708,
    "data": {
      "x": 1209,
      "y": 1019
    }
  },
  {
    "t": "mouse_move",
    "dt": 5.759792899945751,
    "data": {
      "x": 1212,
      "y": 1016
    }
  },
  {
    "t": "mouse_move",
    "dt": 5.767748599988408,
    "data": {
      "x": 1214,
      "y": 1011
    }
  },
  {
    "t": "mouse_move",
    "dt": 5.775734500028193,
    "data": {
      "x": 1218,
      "y": 1004
    }
  },
  {
    "t": "mouse_move",
    "dt": 5.783715200028382,
    "data": {
      "x": 1224,
      "y": 995
    }
  },
  {
    "t": "mouse_move",
    "dt": 5.7917111000278965,
    "data": {
      "x": 1230,
      "y": 986
    }
  },
  {
    "t": "mouse_move",
    "dt": 5.799692000029609,
    "data": {
      "x": 1238,
      "y": 973
    }
  },
  {
    "t": "mouse_move",
    "dt": 5.807678599958308,
    "data": {
      "x": 1247,
      "y": 958
    }
  },
  {
    "t": "mouse_move",
    "dt": 5.8157355999574065,
    "data": {
      "x": 1257,
      "y": 942
    }
  },
  {
    "t": "mouse_move",
    "dt": 5.823722200002521,
    "data": {
      "x": 1268,
      "y": 920
    }
  },
  {
    "t": "mouse_move",
    "dt": 5.831734000006691,
    "data": {
      "x": 1280,
      "y": 893
    }
  },
  {
    "t": "mouse_move",
    "dt": 5.839700000011362,
    "data": {
      "x": 1293,
      "y": 863
    }
  },
  {
    "t": "mouse_move",
    "dt": 5.847701699938625,
    "data": {
      "x": 1305,
      "y": 836
    }
  },
  {
    "t": "mouse_move",
    "dt": 5.855766499997117,
    "data": {
      "x": 1317,
      "y": 810
    }
  },
  {
    "t": "mouse_move",
    "dt": 5.86370360001456,
    "data": {
      "x": 1330,
      "y": 783
    }
  },
  {
    "t": "mouse_move",
    "dt": 5.871755099971779,
    "data": {
      "x": 1345,
      "y": 752
    }
  },
  {
    "t": "mouse_move",
    "dt": 5.879767099977471,
    "data": {
      "x": 1358,
      "y": 725
    }
  },
  {
    "t": "mouse_move",
    "dt": 5.887742799939588,
    "data": {
      "x": 1371,
      "y": 695
    }
  },
  {
    "t": "mouse_move",
    "dt": 5.89574339997489,
    "data": {
      "x": 1384,
      "y": 661
    }
  },
  {
    "t": "mouse_move",
    "dt": 5.903783299960196,
    "data": {
      "x": 1395,
      "y": 631
    }
  },
  {
    "t": "mouse_move",
    "dt": 5.911768799996935,
    "data": {
      "x": 1402,
      "y": 606
    }
  },
  {
    "t": "mouse_move",
    "dt": 5.919753000023775,
    "data": {
      "x": 1409,
      "y": 588
    }
  },
  {
    "t": "mouse_move",
    "dt": 5.927685600006953,
    "data": {
      "x": 1416,
      "y": 571
    }
  },
  {
    "t": "mouse_move",
    "dt": 5.9358121999539435,
    "data": {
      "x": 1421,
      "y": 557
    }
  },
  {
    "t": "mouse_move",
    "dt": 5.943773900042288,
    "data": {
      "x": 1425,
      "y": 544
    }
  },
  {
    "t": "mouse_move",
    "dt": 5.951767000020482,
    "data": {
      "x": 1430,
      "y": 532
    }
  },
  {
    "t": "mouse_move",
    "dt": 5.959772399975918,
    "data": {
      "x": 1435,
      "y": 519
    }
  },
  {
    "t": "mouse_move",
    "dt": 5.967779299942777,
    "data": {
      "x": 1439,
      "y": 508
    }
  },
  {
    "t": "mouse_move",
    "dt": 5.97575440001674,
    "data": {
      "x": 1442,
      "y": 498
    }
  },
  {
    "t": "mouse_move",
    "dt": 5.9837700999341905,
    "data": {
      "x": 1447,
      "y": 487
    }
  },
  {
    "t": "mouse_move",
    "dt": 5.9917773000197485,
    "data": {
      "x": 1451,
      "y": 478
    }
  },
  {
    "t": "mouse_move",
    "dt": 5.999713400029577,
    "data": {
      "x": 1454,
      "y": 471
    }
  },
  {
    "t": "mouse_move",
    "dt": 6.007763499976136,
    "data": {
      "x": 1458,
      "y": 466
    }
  },
  {
    "t": "mouse_move",
    "dt": 6.01577699999325,
    "data": {
      "x": 1462,
      "y": 461
    }
  },
  {
    "t": "mouse_move",
    "dt": 6.023733500041999,
    "data": {
      "x": 1464,
      "y": 456
    }
  },
  {
    "t": "mouse_move",
    "dt": 6.031763899954967,
    "data": {
      "x": 1468,
      "y": 451
    }
  },
  {
    "t": "mouse_move",
    "dt": 6.039792699972168,
    "data": {
      "x": 1472,
      "y": 446
    }
  },
  {
    "t": "mouse_move",
    "dt": 6.047778600011952,
    "data": {
      "x": 1476,
      "y": 442
    }
  },
  {
    "t": "mouse_move",
    "dt": 6.0557432000059634,
    "data": {
      "x": 1481,
      "y": 437
    }
  },
  {
    "t": "mouse_move",
    "dt": 6.063750399975106,
    "data": {
      "x": 1487,
      "y": 431
    }
  },
  {
    "t": "mouse_move",
    "dt": 6.071752900024876,
    "data": {
      "x": 1490,
      "y": 426
    }
  },
  {
    "t": "mouse_move",
    "dt": 6.0797524999361485,
    "data": {
      "x": 1494,
      "y": 421
    }
  },
  {
    "t": "mouse_move",
    "dt": 6.087739199982025,
    "data": {
      "x": 1498,
      "y": 416
    }
  },
  {
    "t": "mouse_move",
    "dt": 6.095673799980432,
    "data": {
      "x": 1502,
      "y": 412
    }
  },
  {
    "t": "mouse_move",
    "dt": 6.1036941999336705,
    "data": {
      "x": 1505,
      "y": 409
    }
  },
  {
    "t": "mouse_move",
    "dt": 6.111729700001888,
    "data": {
      "x": 1509,
      "y": 406
    }
  },
  {
    "t": "mouse_move",
    "dt": 6.119721499970183,
    "data": {
      "x": 1511,
      "y": 404
    }
  },
  {
    "t": "mouse_move",
    "dt": 6.127700199955143,
    "data": {
      "x": 1514,
      "y": 402
    }
  },
  {
    "t": "mouse_move",
    "dt": 6.135701999999583,
    "data": {
      "x": 1516,
      "y": 400
    }
  },
  {
    "t": "mouse_move",
    "dt": 6.143675999948755,
    "data": {
      "x": 1520,
      "y": 398
    }
  },
  {
    "t": "mouse_move",
    "dt": 6.151654399931431,
    "data": {
      "x": 1523,
      "y": 395
    }
  },
  {
    "t": "mouse_move",
    "dt": 6.1596633000299335,
    "data": {
      "x": 1526,
      "y": 394
    }
  },
  {
    "t": "mouse_move",
    "dt": 6.167744399979711,
    "data": {
      "x": 1530,
      "y": 393
    }
  },
  {
    "t": "mouse_move",
    "dt": 6.175717800040729,
    "data": {
      "x": 1533,
      "y": 391
    }
  },
  {
    "t": "mouse_move",
    "dt": 6.183774300036021,
    "data": {
      "x": 1536,
      "y": 390
    }
  },
  {
    "t": "mouse_move",
    "dt": 6.1917497999966145,
    "data": {
      "x": 1539,
      "y": 389
    }
  },
  {
    "t": "mouse_move",
    "dt": 6.199751500040293,
    "data": {
      "x": 1543,
      "y": 387
    }
  },
  {
    "t": "mouse_move",
    "dt": 6.207766599953175,
    "data": {
      "x": 1546,
      "y": 384
    }
  },
  {
    "t": "mouse_move",
    "dt": 6.2157548000104725,
    "data": {
      "x": 1551,
      "y": 382
    }
  },
  {
    "t": "mouse_move",
    "dt": 6.223617300041951,
    "data": {
      "x": 1556,
      "y": 380
    }
  },
  {
    "t": "mouse_move",
    "dt": 6.2317304000025615,
    "data": {
      "x": 1559,
      "y": 377
    }
  },
  {
    "t": "mouse_move",
    "dt": 6.239748999942094,
    "data": {
      "x": 1564,
      "y": 375
    }
  },
  {
    "t": "mouse_move",
    "dt": 6.247830200009048,
    "data": {
      "x": 1567,
      "y": 373
    }
  },
  {
    "t": "mouse_move",
    "dt": 6.25576029997319,
    "data": {
      "x": 1571,
      "y": 369
    }
  },
  {
    "t": "mouse_move",
    "dt": 6.26375799998641,
    "data": {
      "x": 1574,
      "y": 367
    }
  },
  {
    "t": "mouse_move",
    "dt": 6.271738199982792,
    "data": {
      "x": 1578,
      "y": 365
    }
  },
  {
    "t": "mouse_move",
    "dt": 6.279769300017506,
    "data": {
      "x": 1581,
      "y": 361
    }
  },
  {
    "t": "mouse_move",
    "dt": 6.287704100017436,
    "data": {
      "x": 1584,
      "y": 359
    }
  },
  {
    "t": "mouse_move",
    "dt": 6.295781399938278,
    "data": {
      "x": 1587,
      "y": 357
    }
  },
  {
    "t": "mouse_move",
    "dt": 6.30376229993999,
    "data": {
      "x": 1589,
      "y": 356
    }
  },
  {
    "t": "mouse_move",
    "dt": 6.311768100014888,
    "data": {
      "x": 1591,
      "y": 355
    }
  },
  {
    "t": "mouse_move",
    "dt": 6.319759199977852,
    "data": {
      "x": 1592,
      "y": 354
    }
  },
  {
    "t": "mouse_move",
    "dt": 6.32774979993701,
    "data": {
      "x": 1592,
      "y": 353
    }
  },
  {
    "t": "mouse_move",
    "dt": 6.335833100019954,
    "data": {
      "x": 1593,
      "y": 353
    }
  },
  {
    "t": "mouse_move",
    "dt": 6.343800200033002,
    "data": {
      "x": 1594,
      "y": 352
    }
  },
  {
    "t": "mouse_move",
    "dt": 6.351752100046724,
    "data": {
      "x": 1595,
      "y": 351
    }
  },
  {
    "t": "mouse_move",
    "dt": 6.359750099945813,
    "data": {
      "x": 1596,
      "y": 351
    }
  },
  {
    "t": "mouse_move",
    "dt": 6.367783599998802,
    "data": {
      "x": 1597,
      "y": 350
    }
  },
  {
    "t": "mouse_move",
    "dt": 6.375769300037064,
    "data": {
      "x": 1599,
      "y": 349
    }
  },
  {
    "t": "mouse_move",
    "dt": 6.383790699997917,
    "data": {
      "x": 1601,
      "y": 348
    }
  },
  {
    "t": "mouse_move",
    "dt": 6.391761900042184,
    "data": {
      "x": 1603,
      "y": 347
    }
  },
  {
    "t": "mouse_move",
    "dt": 6.399704099982046,
    "data": {
      "x": 1605,
      "y": 345
    }
  },
  {
    "t": "mouse_move",
    "dt": 6.407711299951188,
    "data": {
      "x": 1607,
      "y": 344
    }
  },
  {
    "t": "mouse_move",
    "dt": 6.415714800008573,
    "data": {
      "x": 1609,
      "y": 341
    }
  },
  {
    "t": "mouse_move",
    "dt": 6.423671999946237,
    "data": {
      "x": 1610,
      "y": 341
    }
  },
  {
    "t": "mouse_move",
    "dt": 6.43196529999841,
    "data": {
      "x": 1611,
      "y": 340
    }
  },
  {
    "t": "mouse_move",
    "dt": 6.439768300042488,
    "data": {
      "x": 1612,
      "y": 339
    }
  },
  {
    "t": "mouse_move",
    "dt": 6.447670700028539,
    "data": {
      "x": 1612,
      "y": 338
    }
  },
  {
    "t": "mouse_move",
    "dt": 6.455650900024921,
    "data": {
      "x": 1613,
      "y": 337
    }
  },
  {
    "t": "mouse_move",
    "dt": 6.463678100029938,
    "data": {
      "x": 1614,
      "y": 336
    }
  },
  {
    "t": "mouse_move",
    "dt": 6.471749600023031,
    "data": {
      "x": 1615,
      "y": 335
    }
  },
  {
    "t": "mouse_move",
    "dt": 6.479685300029814,
    "data": {
      "x": 1616,
      "y": 335
    }
  },
  {
    "t": "mouse_move",
    "dt": 6.487770300009288,
    "data": {
      "x": 1617,
      "y": 335
    }
  },
  {
    "t": "mouse_move",
    "dt": 6.495752500020899,
    "data": {
      "x": 1618,
      "y": 334
    }
  },
  {
    "t": "mouse_move",
    "dt": 6.503743099980056,
    "data": {
      "x": 1618,
      "y": 334
    }
  },
  {
    "t": "mouse_move",
    "dt": 6.511792200035416,
    "data": {
      "x": 1619,
      "y": 333
    }
  },
  {
    "t": "mouse_move",
    "dt": 6.519678200013004,
    "data": {
      "x": 1620,
      "y": 332
    }
  },
  {
    "t": "mouse_move",
    "dt": 6.527731199981645,
    "data": {
      "x": 1621,
      "y": 331
    }
  },
  {
    "t": "mouse_move",
    "dt": 6.53573789994698,
    "data": {
      "x": 1622,
      "y": 330
    }
  },
  {
    "t": "mouse_move",
    "dt": 6.543788300012238,
    "data": {
      "x": 1623,
      "y": 329
    }
  },
  {
    "t": "mouse_move",
    "dt": 6.551750099984929,
    "data": {
      "x": 1623,
      "y": 329
    }
  },
  {
    "t": "mouse_move",
    "dt": 6.559755399939604,
    "data": {
      "x": 1624,
      "y": 328
    }
  },
  {
    "t": "mouse_move",
    "dt": 6.567757999990135,
    "data": {
      "x": 1624,
      "y": 327
    }
  },
  {
    "t": "mouse_move",
    "dt": 6.575696900021285,
    "data": {
      "x": 1624,
      "y": 326
    }
  },
  {
    "t": "mouse_move",
    "dt": 6.583783800015226,
    "data": {
      "x": 1625,
      "y": 326
    }
  },
  {
    "t": "mouse_click",
    "dt": 6.720549799967557,
    "data": {
      "x": 1625,
      "y": 326,
      "button": "left",
      "pressed": true
    }
  },
  {
    "t": "mouse_click",
    "dt": 6.767997300019488,
    "data": {
      "x": 1625,
      "y": 326,
      "button": "left",
      "pressed": false
    }
  }
]